README.md
setup.py
PyDexter/__init__.py
PyDexter/main.py
PyDexter.egg-info/PKG-INFO
PyDexter.egg-info/SOURCES.txt
PyDexter.egg-info/dependency_links.txt
PyDexter.egg-info/top_level.txt