Metadata-Version: 1.0
Name: PyDexter
Version: 0.0.2
Summary: Simple plotting for Python. Render charts in the browser with simple Python syntax.
Home-page: UNKNOWN
Author: Nathan Epstein
Author-email: _@nepste.in
License: MIT
Keywords: data visualization
Platform: UNKNOWN
